calculator.py
tc_ds_2023_calculator-1.0.0.dist-info/LICENSE.TXT
tc_ds_2023_calculator-1.0.0.dist-info/METADATA
tc_ds_2023_calculator-1.0.0.dist-info/WHEEL
tc_ds_2023_calculator-1.0.0.dist-info/top_level.txt
tc_ds_2023_calculator-1.0.0.dist-info/RECORD
