Metadata-Version: 2.1
Name: tc-ds-2023-calculator
Version: 1.0.0
Summary: Contains Calculator Class    used for performing basic arithmetic operations
License-File: LICENSE.TXT
